dj_upload_to.py
dj_upload_to-1.1.dist-info/metadata.json
dj_upload_to-1.1.dist-info/WHEEL
dj_upload_to-1.1.dist-info/METADATA
dj_upload_to-1.1.dist-info/DESCRIPTION.rst
dj_upload_to-1.1.dist-info/RECORD
dj_upload_to-1.1.dist-info/top_level.txt
