Metadata-Version: 2.0
Name: dj-upload-to
Version: 1.1
Summary: Small application that simplifies naming of uploaded files
Home-page: https://github.com/marazmiki/dj-upload-to
Author: Mikhail Porokhovnichenko
Author-email: marazmiki@gmail.com
License: UNKNOWN
Platform: UNKNOWN
Classifier: Environment :: Web Environment
Classifier: Programming Language :: Python :: 2.7
Classifier: Programming Language :: Python :: 3.3
Classifier: Programming Language :: Python :: 3.4
Classifier: Framework :: Django
